daylily_cognito/__init__.py
daylily_cognito/auth.py
daylily_cognito/cli.py
daylily_cognito/config.py
daylily_cognito/fastapi.py
daylily_cognito/jwks.py
daylily_cognito/oauth.py
daylily_cognito/tokens.py
daylily_cognito-0.1.10.dist-info/licenses/LICENSE
daylily_cognito-0.1.10.dist-info/METADATA
daylily_cognito-0.1.10.dist-info/WHEEL
daylily_cognito-0.1.10.dist-info/entry_points.txt
daylily_cognito-0.1.10.dist-info/top_level.txt
daylily_cognito-0.1.10.dist-info/RECORD
