Metadata-Version: 2.4
Name: daylily-cognito
Version: 0.1.10
Summary: Shared Cognito authentication library for FastAPI + Jinja2 web apps
Author-email: Daylily Informatics <daylily@daylilyinformatics.com>
License-Expression: MIT
Project-URL: Homepage, https://github.com/Daylily-Informatics/daylily-cognito
Project-URL: Repository, https://github.com/Daylily-Informatics/daylily-cognito
Keywords: aws,cognito,authentication,fastapi,jwt,oauth2
Classifier: Development Status :: 3 - Alpha
Classifier: Intended Audience :: Developers
Classifier: Operating System :: OS Independent
Classifier: Programming Language :: Python :: 3
Classifier: Programming Language :: Python :: 3.9
Classifier: Programming Language :: Python :: 3.10
Classifier: Programming Language :: Python :: 3.11
Classifier: Programming Language :: Python :: 3.12
Classifier: Programming Language :: Python :: 3.13
Classifier: Framework :: FastAPI
Classifier: Topic :: Security
Classifier: Topic :: Internet :: WWW/HTTP :: Session
Classifier: Typing :: Typed
Requires-Python: >=3.9
License-File: LICENSE
Requires-Dist: boto3>=1.26.0
Requires-Dist: fastapi>=0.104.0
Requires-Dist: typer>=0.9.0
Requires-Dist: rich>=13.0.0
Provides-Extra: auth
Requires-Dist: python-jose[cryptography]>=3.3.0; extra == "auth"
Provides-Extra: dev
Requires-Dist: pytest>=7.4.0; extra == "dev"
Requires-Dist: pytest-cov>=4.1.0; extra == "dev"
Requires-Dist: ruff>=0.1.0; extra == "dev"
Dynamic: license-file
